kothon/__init__.py
kothon/__init__.pyi
kothon/pipe.py
kothon/pipe.pyi
kothon/py.typed
kothon/_utils/__init__.py
kothon/_utils/__init__.pyi
kothon/_utils/type_utils.py
kothon/_utils/type_utils.pyi
kothon/functions/__init__.py
kothon/functions/__init__.pyi
kothon/functions/aggregation.py
kothon/functions/aggregation.pyi
kothon/functions/sequence.py
kothon/functions/sequence.pyi
kothon/iterable/__init__.py
kothon/iterable/__init__.pyi
kothon/iterable/seq.py
kothon/iterable/seq.pyi
kothon-0.3.2.dist-info/LICENSE
kothon-0.3.2.dist-info/METADATA
kothon-0.3.2.dist-info/WHEEL
kothon-0.3.2.dist-info/top_level.txt
kothon-0.3.2.dist-info/RECORD
