Metadata-Version: 2.1
Name: kothon
Version: 0.3.2
Summary: A Python library that brings Kotlin's Sequence class functionalities and the power of functional programming to Python for more expressive and efficient data processing.
Author-email: Klaus Happacher <k.happacher@gmail.com>
Maintainer-email: Klaus Happacher <k.happacher@gmail.com>
License: MIT License
Project-URL: Homepage, https://github.com/klahap/kothon
Project-URL: Documentation, https://github.com/klahap/kothon/blob/main/README.md
Project-URL: Repository, https://github.com/klahap/kothon.git
Project-URL: Issues, https://github.com/klahap/kothon/issues
Keywords: python,functional-programming,kotlin-sequences,data-processing,lazy-evaluation,type-hints
Classifier: Development Status :: 5 - Production/Stable
Classifier: Programming Language :: Python
Requires-Python: >=3.9
License-File: LICENSE
